{
  "version": "7",
  "dialect": "postgresql",
  "entries": [
    {
      "idx": 0,
      "version": "7",
      "when": 1731023699756,
      "tag": "0000_great_wraith",
      "breakpoints": true
    },
    {
      "idx": 1,
      "version": "7",
      "when": 1731023723771,
      "tag": "0001_right_marvex",
      "breakpoints": true
    },
    {
      "idx": 2,
      "version": "7",
      "when": 1731023735572,
      "tag": "0002_silky_malcolm_colcord",
      "breakpoints": true
    },
    {
      "idx": 3,
      "version": "7",
      "when": 1731023778996,
      "tag": "0003_fuzzy_fixer",
      "breakpoints": true
    },
    {
      "idx": 4,
      "version": "7",
      "when": 1731023796265,
      "tag": "0004_icy_hydra",
      "breakpoints": true
    },
    {
      "idx": 5,
      "version": "7",
      "when": 1731023823541,
      "tag": "0005_optimal_excalibur",
      "breakpoints": true
    },
    {
      "idx": 6,
      "version": "7",
      "when": 1731023849927,
      "tag": "0006_soft_master_mold",
      "breakpoints": true
    },
    {
      "idx": 7,
      "version": "7",
      "when": 1731023877223,
      "tag": "0007_regular_mulholland_black",
      "breakpoints": true
    },
    {
      "idx": 8,
      "version": "7",
      "when": 1731023910462,
      "tag": "0008_overjoyed_unus",
      "breakpoints": true
    },
    {
      "idx": 9,
      "version": "7",
      "when": 1731023983549,
      "tag": "0009_same_outlaw_kid",
      "breakpoints": true
    },
    {
      "idx": 10,
      "version": "7",
      "when": 1731024026194,
      "tag": "0010_happy_smiling_tiger",
      "breakpoints": true
    },
    {
      "idx": 11,
      "version": "7",
      "when": 1731024117824,
      "tag": "0011_jittery_apocalypse",
      "breakpoints": true
    },
    {
      "idx": 12,
      "version": "7",
      "when": 1731024178585,
      "tag": "0012_clammy_iron_patriot",
      "breakpoints": true
    },
    {
      "idx": 13,
      "version": "7",
      "when": 1731024346553,
      "tag": "0013_safe_warlock",
      "breakpoints": true
    },
    {
      "idx": 14,
      "version": "7",
      "when": 1731024413589,
      "tag": "0014_living_wallow",
      "breakpoints": true
    },
    {
      "idx": 15,
      "version": "7",
      "when": 1735413473027,
      "tag": "0015_melted_valeria_richards",
      "breakpoints": true
    },
    {
      "idx": 16,
      "version": "7",
      "when": 1735414735513,
      "tag": "0016_tranquil_bulldozer",
      "breakpoints": true
    },
    {
      "idx": 17,
      "version": "7",
      "when": 1735415361979,
      "tag": "0017_youthful_tomorrow_man",
      "breakpoints": true
    },
    {
      "idx": 18,
      "version": "7",
      "when": 1735426454737,
      "tag": "0018_abandoned_justice",
      "breakpoints": true
    }
  ]
}